{
  "name": "Philipp Eschenbach",
  "info": {
    "label": "Chief Technology Officer",
    "image": "https://avatars1.githubusercontent.com/u/1596052",
    "brief": "CTO with expertise in Java, Kotlin, Micronaut, AI, and cloud-native architectures. Passionate about scaling teams and modernizing tech stacks."
  },
  "contact": {
    "email": "philipp@eschenbach.co",
    "website": "https://eschenbach.co"
  },
  "meta": {
    "format": "FRESH@^1.0.0-beta",
    "modified": "2025-02-26T12:57:28.040Z"
  },
  "location": {
    "address": "Berlin, Germany"
  },
  "employment": {
    "history": [
      {
        "position": "Chief Technology Officer",
        "employer": "Legal Hero GmbH",
        "summary": "Building and scaling the engineering team, modernizing tech stack, and driving AI initiatives.",
        "current": true,
        "start": "2023-11-01",
        "keywords": [],
        "highlights": [
          "Scaled the engineering \"team\" of 1 full-stack Developer, growing it to 12 developers with strong expertise in Backend, Frontend, AI and DevOps.",
          "Migrated from a monolithic Groovy (Grails) Application to a modern microservices setup using Kotlin and Micronaut, significantly improving performance, scalability, and maintainability.",
          "Implemented a Kubernetes (K8s) cluster, improving system reliability and scalability while reducing deployment complexity.",
          "Defined and executed the technology roadmap, aligning engineering efforts with business objectives.",
          "Launched AI-driven automation projects, including self-trained models to support operational teams and enhance platform effectiveness."
        ]
      },
      {
        "position": "Chief Technology Officer, (late) Co-Foudner and Managing Director",
        "employer": "Culcha GmbH",
        "summary": "Led technical development, moving the platform from MVP to production-ready status.",
        "current": true,
        "start": "2021-04-01",
        "keywords": [],
        "highlights": [
          "Transitioned the product from an MVP to a fully scalable, production-ready application, ensuring high availability and performance.",
          "Designed and implemented a backend architecture using Kotlin and Micronaut, reducing response times and improving system maintainability.",
          "Led a product organization of 8 people (engineering, product, design), improving cross-functional collaboration and accelerating development speed.",
          "Developed and integrated predictive analytics to enhance user engagement and content creation."
        ]
      },
      {
        "position": "VP Engineering",
        "employer": "uberall GmbH",
        "summary": "Scaled the engineering team and introduced microservices architecture.",
        "start": "2018-08-01",
        "end": "2021-01-31",
        "keywords": [],
        "highlights": [
          "Grew the engineering team from 20 to 60 developers, improving hiring processes and fostering a strong engineering culture.",
          "Transitioned the development structure from a traditional backend/frontend model to a squad-based engineering setup, increasing agility and cross-team collaboration.",
          "Led all Engineering Managers, ensuring effective leadership and alignment across teams.",
          "Introduced microservices with Micronaut, reducing system complexity and improving scalability."
        ]
      },
      {
        "position": "Lead Backend Developer",
        "employer": "uberall GmbH",
        "summary": "Led the backend team and modernized infrastructure.",
        "start": "2013-07-01",
        "end": "2018-07-30",
        "keywords": [],
        "highlights": [
          "Managed a team of 7 backend developers, fostering growth and technical excellence.",
          "Designed and deployed cloud infrastructure on AWS, improving system resilience and reducing costs.",
          "Executed a zero-downtime migration to AWS, ensuring smooth service transition without impact on customers.",
          "Implemented Docker and Jenkins-based CI/CD pipelines, significantly accelerating deployment cycles."
        ]
      }
    ]
  },
  "skills": {
    "sets": [
      {
        "name": "Development",
        "skills": [
          "Kotlin",
          "Java",
          "Groovy",
          "Grails",
          "React",
          "TypeScript",
          "Node.js"
        ]
      },
      {
        "name": "Architecture & Infrastructure",
        "skills": [
          "Microservices",
          "Micronaut",
          "Spring Boot",
          "Event-Driven Architectures",
          "Scalable Systems"
        ]
      },
      {
        "name": "DevOps",
        "skills": [
          "Kubernetes",
          "AWS",
          "Docker",
          "Terraform",
          "CI/CD",
          "Jenkins",
          "GitHub Actions"
        ]
      },
      {
        "name": "AI & Data Engineering",
        "skills": [
          "AI/ML Model Training",
          "Predictive Analytics",
          "NLP",
          "Data Pipelines"
        ]
      },
      {
        "name": "Leadership & Strategy",
        "skills": [
          "Engineering Leadership",
          "Scaling Teams",
          "Agile & Squad-Based Structures",
          "Technology Roadmaps"
        ]
      }
    ]
  },
  "social": [
    {
      "label": "GitHub",
      "network": "GitHub",
      "url": "https://github.com/peh",
      "user": "peh"
    },
    {
      "label": "linkedin",
      "network": "linkedin",
      "url": "https://www.linkedin.com/profile/view?id=AAMAAA-vj78BH8V8eiNPceidtsXmYCIIlDCrvt4",
      "user": "Philipp Eschenbach"
    }
  ],
  "languages": [
    {
      "language": "German",
      "fluency": "Native speaker"
    },
    {
      "language": "English",
      "fluency": "Fluent"
    }
  ]
}